macaca/__init__.py
macaca/asserters.py
macaca/command.py
macaca/keys.py
macaca/locator.py
macaca/remote_invoker.py
macaca/util.py
macaca/webdriver.py
macaca/webdriverexception.py
macaca/webdriverresult.py
macaca/webelement.py
wd-1.0.0.dist-info/DESCRIPTION.rst
wd-1.0.0.dist-info/METADATA
wd-1.0.0.dist-info/RECORD
wd-1.0.0.dist-info/WHEEL
wd-1.0.0.dist-info/metadata.json
wd-1.0.0.dist-info/top_level.txt
