Metadata-Version: 2.0
Name: wd
Version: 1.0.0
Summary: Macaca Python Client
Home-page: https://github.com/macacajs/wd.py
Author: Zichen Zhu
Author-email: zic.zhu@gmail.com
License: MIT
Keywords: macaca,webdriver,uitest,mobile automation,e2e
Platform: UNKNOWN
Classifier: Development Status :: 3 - Alpha
Classifier: Intended Audience :: Developers
Classifier: Topic :: Software Development :: Build Tools
Classifier: License :: OSI Approved :: MIT License
Classifier: Programming Language :: Python :: 2.7
Classifier: Programming Language :: Python :: 3.4
Classifier: Programming Language :: Python :: 3.5
Requires-Dist: enum34
Requires-Dist: requests
Requires-Dist: retrying
Provides-Extra: test
Requires-Dist: coverage; extra == 'test'
Requires-Dist: pytest; extra == 'test'
Requires-Dist: pytest-cov; extra == 'test'
Requires-Dist: pytest-xdist; extra == 'test'
Requires-Dist: responses; extra == 'test'
Requires-Dist: tox; extra == 'test'
